src/__init__.py
src/extractor.py
src/main.py
src/tree.py
src/utils.py
src/version.py
file_content_extractor-0.3.7.dist-info/LICENCE
file_content_extractor-0.3.7.dist-info/METADATA
file_content_extractor-0.3.7.dist-info/WHEEL
file_content_extractor-0.3.7.dist-info/entry_points.txt
file_content_extractor-0.3.7.dist-info/top_level.txt
file_content_extractor-0.3.7.dist-info/RECORD
