Metadata-Version: 2.1
Name: file-content-extractor
Version: 0.3.7
Summary: A tool to extract content from text files in a directory, with options to ignore certain files and directories.
Home-page: https://github.com/joonheeu/file-content-extractor
Author: Daniel
Author-email: daniel@udit.one
Classifier: Programming Language :: Python :: 3
Classifier: License :: OSI Approved :: MIT License
Classifier: Operating System :: OS Independent
Requires-Python: >=3.6
License-File: LICENCE
Requires-Dist: anytree
Requires-Dist: pathspec
